MANIFEST.in
README.md
build.py
requirements-dev.txt
requirements.txt
setup.py
dynamic_service.egg-info/PKG-INFO
dynamic_service.egg-info/SOURCES.txt
dynamic_service.egg-info/dependency_links.txt
dynamic_service.egg-info/requires.txt
dynamic_service.egg-info/top_level.txt
dynamic_service/endpoints/__init__.py
dynamic_service/endpoints/base.py
dynamic_service/endpoints/data.py
dynamic_service/endpoints/engine.py
dynamic_service/endpoints/exceptions.py
dynamic_service/endpoints/process.py
dynamic_service/service/__init__.py
dynamic_service/service/base.py
dynamic_service/service/http.py